{
    "key": "group_5b2214c0b16ad",
    "title": "_mod_WorkHeader",
    "fields": [
        {
            "key": "field_5b2214c0c4550",
            "label": "Image",
            "name": "image",
            "type": "image_crop",
            "instructions": "Mida mínima 3600px d'ample per 1773px d'alt",
            "required": 0,
            "conditional_logic": 0,
            "wrapper": {
                "width": "50",
                "class": "",
                "id": ""
            },
            "crop_type": "hard",
            "target_size": "custom",
            "width": 1800,
            "height": 886,
            "renditions": "1300,1000,450",
            "preview_size": "medium",
            "force_crop": "yes",
            "save_in_media_library": "yes",
            "retina_mode": "yes",
            "save_format": "url",
            "library": "uploadedTo"
        },
        {
            "key": "field_5b2214c0c46b7",
            "label": "Video",
            "name": "video",
            "type": "file",
            "instructions": "Mida HD",
            "required": 0,
            "conditional_logic": 0,
            "wrapper": {
                "width": "50",
                "class": "",
                "id": ""
            },
            "return_format": "array",
            "library": "uploadedTo",
            "min_size": "",
            "max_size": "",
            "mime_types": ""
        }
    ],
    "location": [
        [
            {
                "param": "post_type",
                "operator": "==",
                "value": "post"
            }
        ]
    ],
    "menu_order": 0,
    "position": "normal",
    "style": "default",
    "label_placement": "top",
    "instruction_placement": "label",
    "hide_on_screen": "",
    "active": 0,
    "description": "",
    "modified": 1528961977
}